fyang_util/Nacos.py
fyang_util/__init__.py
fyang_util/apscheduler_util.py
fyang_util/common_utils.py
fyang_util/config_util.py
fyang_util/constants.py
fyang_util/datetime_util.py
fyang_util/debug_utils.py
fyang_util/kafka_util.py
fyang_util/logger_util.py
fyang_util/mongo_util.py
fyang_util/multiprocess_util.py
fyang_util/mysql_util.py
fyang_util/test.py
fyang_utils-0.0.1.3.dist-info/LICENSE
fyang_utils-0.0.1.3.dist-info/METADATA
fyang_utils-0.0.1.3.dist-info/WHEEL
fyang_utils-0.0.1.3.dist-info/top_level.txt
fyang_utils-0.0.1.3.dist-info/zip-safe
fyang_utils-0.0.1.3.dist-info/RECORD
