Metadata-Version: 2.1
Name: fyang_utils
Version: 0.0.1.3
Summary: common tools for dev
Author: fyang
Classifier: Programming Language :: Python :: 3
Classifier: License :: OSI Approved :: MIT License
Classifier: Operating System :: OS Independent
Requires-Python: >=3.6
License-File: LICENSE
Requires-Dist: loguru
Requires-Dist: configparser ==5.0.2
Requires-Dist: pymongo ==3.12.0
Requires-Dist: PyMySQL ==1.0.2
Requires-Dist: DateTime ==4.3
Requires-Dist: redis ==3.5.3
Requires-Dist: DBUtils ==1.3
Requires-Dist: clickhouse-driver ==0.2.2
Requires-Dist: APScheduler ==3.8.0
Requires-Dist: oss2 ==2.15.0
Requires-Dist: kafka-python ==2.0.2
Requires-Dist: xhtml2pdf ==0.2.5
Requires-Dist: Jinja2 ==2.11.3
Requires-Dist: odps ==3.5.1
Requires-Dist: openpyxl ==3.0.9
Requires-Dist: netifaces ==0.11.0
Requires-Dist: nacos-sdk-python ==0.1.6
